authro/__init__.py
authro-0.0.1.dist-info/METADATA
authro-0.0.1.dist-info/WHEEL
authro-0.0.1.dist-info/top_level.txt
authro-0.0.1.dist-info/RECORD
