Metadata-Version: 2.1
Name: authro
Version: 0.0.1
Summary: An identity platform
Author: Muthu
Author-email: contact@muthupandian.in
